setup.py
medulla_toolkit.egg-info/PKG-INFO
medulla_toolkit.egg-info/SOURCES.txt
medulla_toolkit.egg-info/dependency_links.txt
medulla_toolkit.egg-info/not-zip-safe
medulla_toolkit.egg-info/requires.txt
medulla_toolkit.egg-info/top_level.txt
toolkit/__init__.py
toolkit/api.py
toolkit/code_status_tkt.py
toolkit/connection_setting.py
toolkit/utility.py