Metadata-Version: 2.1
Name: medulla-toolkit
Version: 0.1
Summary: Toolkit for the Shopfloor endpoints.
Author: Medulla
